feds_shield/__init__.py
feds_shield/alphabet_load.py
feds_shield/bi_key.py
feds_shield/centerion.py
feds_shield/crypt_env.py
feds_shield/decrypt_env.py
feds_shield/file_ops.py
feds_shield/firing_agent.py
feds_shield/py_stat_test.py
feds_shield/structure.py
feds_shield-0.0.4.dist-info/licenses/LICENSE
feds_shield-0.0.4.dist-info/METADATA
feds_shield-0.0.4.dist-info/WHEEL
feds_shield-0.0.4.dist-info/top_level.txt
feds_shield-0.0.4.dist-info/RECORD
