Metadata-Version: 2.4
Name: feds_shield
Version: 0.0.4
Summary: A simple cryptographic program
Home-page: https://github.com/Changissnz/feds_shield
Author: Richard Pham
Author-email: Richard Pham <phamrichard45@gmail.com>
License-Expression: GPL-3.0
Project-URL: Homepage, https://github.com/changissnz/feds_shield
Classifier: Programming Language :: Python :: 3
Classifier: Operating System :: OS Independent
Requires-Python: >=3.9
License-File: LICENSE
Dynamic: author
Dynamic: home-page
Dynamic: license-file
